README.rst
setup.py
awslambdatools/__init__.py
awslambdatools/bedrock_helpers.py
awslambdatools/s3event_helpers.py
awslambdatools/sql_wrappers.py
awslambdatools/utility_functions.py
awslambdatools.egg-info/PKG-INFO
awslambdatools.egg-info/SOURCES.txt
awslambdatools.egg-info/dependency_links.txt
awslambdatools.egg-info/top_level.txt
test/test_bedrock_helpers.py
test/test_s3event_helpers.py
test/test_sql_wrappers.py
test/test_utility_functions.py