Metadata-Version: 2.1
Name: awslambdatools
Version: 0.0.9
Summary: Package for dealing with lambdas running on Python
Author: Edward Velo
Author-email: vattico@gmail.com
Requires-Python: >=3.6
